ABtests/__init__.py
ABtests/analysis/__init__.py
ABtests/analysis/analisys.py
ABtests/analysis/analysis.py
ABtests/resampling/__init__.py
ABtests/resampling/bootstrapping.py
ABtests/stats/__init__.py
ABtests/stats/power.py
ABtests/stats/proportions.py
ABtests/stats/statstest.py
ABtests/stats/version.py
ABtests-0.0.2.1.dist-info/DESCRIPTION.rst
ABtests-0.0.2.1.dist-info/METADATA
ABtests-0.0.2.1.dist-info/RECORD
ABtests-0.0.2.1.dist-info/WHEEL
ABtests-0.0.2.1.dist-info/metadata.json
ABtests-0.0.2.1.dist-info/top_level.txt
tests/__init__.py
tests/test_analysis.py
tests/test_proportions.py
tests/test_statstest.py
utility/__init__.py
utility/plots.py
